README.md
setup.py
ipycov/__init__.py
ipycov/magic.py
ipycov.egg-info/PKG-INFO
ipycov.egg-info/SOURCES.txt
ipycov.egg-info/dependency_links.txt
ipycov.egg-info/not-zip-safe
ipycov.egg-info/requires.txt
ipycov.egg-info/top_level.txt