Metadata-Version: 1.1
Name: ipycov
Version: 0.0.1
Summary: Coverage access via IPython
Home-page: https://pypi.python.org/pypi/ipython-coverage
Author: Santiago Balestrini-Robinson
Author-email: sanbales@gmail.com
License: MIT
Keywords: testing coverage ipython
Platform: UNKNOWN
Classifier: Development Status :: 3 - Alpha
Classifier: Environment :: Console
Classifier: License :: OSI Approved :: MIT License
Classifier: Topic :: Software Development :: Testing
Classifier: Programming Language :: Python :: 3
Classifier: Programming Language :: Python :: 3.4
Classifier: Programming Language :: Python :: 3.5
Classifier: Programming Language :: Python :: 3.6
Classifier: Programming Language :: Python :: 3.7
